{
  "model": {
    "type": "minecraft:select",
    "property": "minecraft:component",
    "component": "minecraft:custom_name",
    "cases": [
      {
        "when": [
          {
            "text": "",
            "extra": [
              {
                "text": "Коробка с боеприпасами",
                "italic": true
              }
            ],
            "italic": false
          }
        ],
        "model": {
          "type": "minecraft:model",
          "model": "ksepsp:item/9_0/other/shulker_box/ammo_box"
        }
      },
      {
        "when": [
          {
            "text": "",
            "extra": [
              {
                "text": "Маленькая коробка с боеприпасами",
                "italic": true
              }
            ],
            "italic": false
          }
        ],
        "model": {
          "type": "minecraft:model",
          "model": "ksepsp:item/9_0/other/shulker_box/small_ammo_box"
        }
      },
      {
        "when": [
          {
            "text": "",
            "extra": [
              {
                "text": "Портфель",
                "italic": true
              }
            ],
            "italic": false
          }
        ],
        "model": {
          "type": "minecraft:model",
          "model": "ksepsp:item/9_0/other/shulker_box/briefcase"
        }
      },
      {
        "when": [
          {
            "text": "",
            "extra": [
              {
                "text": "Кейс",
                "italic": true
              }
            ],
            "italic": false
          }
        ],
        "model": {
          "type": "minecraft:model",
          "model": "ksepsp:item/9_0/other/shulker_box/case"
        }
      },
      {
        "when": [
          {
            "text": "",
            "extra": [
              {
                "text": "Дипломат",
                "italic": true
              }
            ],
            "italic": false
          }
        ],
        "model": {
          "type": "minecraft:model",
          "model": "ksepsp:item/9_0/other/shulker_box/diplomat"
        }
      },
      {
        "when": [
          {
            "text": "",
            "extra": [
              {
                "text": "Металлический кейс",
                "italic": true
              }
            ],
            "italic": false
          }
        ],
        "model": {
          "type": "minecraft:model",
          "model": "ksepsp:item/9_0/other/shulker_box/metal_case"
        }
      },
      {
        "when": [
          {
            "text": "",
            "extra": [
              {
                "text": "Чемодан",
                "italic": true
              }
            ],
            "italic": false
          }
        ],
        "model": {
          "type": "minecraft:model",
          "model": "ksepsp:item/9_0/other/shulker_box/suitcase"
        }
      },
      {
        "when": [
          {
            "text": "",
            "extra": [
              {
                "text": "Наплечная сумка",
                "italic": true
              }
            ],
            "italic": false
          }
        ],
        "model": {
          "type": "minecraft:model",
          "model": "ksepsp:item/9_0/other/shulker_box/handbag"
        }
      },
      {
        "when": [
          {
            "text": "",
            "extra": [
              {
                "text": "Походная сумка",
                "italic": true
              }
            ],
            "italic": false
          }
        ],
        "model": {
          "type": "minecraft:model",
          "model": "ksepsp:item/9_0/other/shulker_box/hiking_backpack"
        }
      },
      {
        "when": [
          {
            "text": "",
            "extra": [
              {
                "text": "Спортивная сумка",
                "italic": true
              }
            ],
            "italic": false
          }
        ],
        "model": {
          "type": "minecraft:select",
          "property": "minecraft:display_context",
          "cases": [
            {
              "when": [
                "firstperson_righthand",
                "thirdperson_righthand",
                "head",
                "ground"
              ],
              "model": {
                "type": "minecraft:model",
                "model": "ksepsp:item/9_0/other/shulker_box/sport_bag"
              }
            }
          ],
          "fallback": {
            "type": "minecraft:model",
            "model": "ksepsp:item/9_0/other/shulker_box/sport_bag_left_hand"
          }
        }
      },
      {
        "when": [
          {
            "text": "",
            "extra": [
              {
                "text": "Большой подарок",
                "italic": true
              }
            ],
            "italic": false
          }
        ],
        "model": {
          "type": "minecraft:model",
          "model": "ksepsp:item/9_0/other/shulker_box/big_present"
        }
      },
      {
        "when": [
          {
            "text": "",
            "extra": [
              {
                "text": "Подарок",
                "italic": true
              }
            ],
            "italic": false
          }
        ],
        "model": {
          "type": "minecraft:model",
          "model": "ksepsp:item/9_0/other/shulker_box/present"
        }
      },
      {
        "when": [
          {
            "text": "",
            "extra": [
              {
                "text": "Ящик для инструментов",
                "italic": true
              }
            ],
            "italic": false
          }
        ],
        "model": {
          "type": "minecraft:model",
          "model": "ksepsp:item/9_0/other/shulker_box/toolbox"
        }
      },
      {
        "when": [
          {
            "text": "",
            "extra": [
              {
                "text": "Посылка",
                "italic": true
              }
            ],
            "italic": false
          }
        ],
        "model": {
          "type": "minecraft:model",
          "model": "ksepsp:item/9_0/other/shulker_box/parcel"
        }
      },
      {
        "when": [
          {
            "text": "",
            "extra": [
              {
                "text": "Аптечка",
                "italic": true
              }
            ],
            "italic": false
          }
        ],
        "model": {
          "type": "minecraft:model",
          "model": "ksepsp:item/9_0/other/shulker_box/medkit"
        }
      },
      {
        "when": [
          {
            "text": "",
            "extra": [
              {
                "text": "Блок сигарет",
                "italic": true
              }
            ],
            "italic": false
          }
        ],
        "model": {
          "type": "minecraft:model",
          "model": "ksepsp:item/9_0/other/shulker_box/cigarette_carton"
        }
      },
      {
        "when": [
          {
            "text": "",
            "extra": [
              {
                "text": "Спортивная сумка с деньгами",
                "italic": true
              }
            ],
            "italic": false
          }
        ],
        "model": {
          "type": "minecraft:model",
          "model": "ksepsp:item/9_0/other/shulker_box/sport_bag_with_money"
        }
      }
    ],
    "fallback": {
      "type": "minecraft:special",
      "model": {
        "type": "minecraft:shulker_box",
        "texture": "minecraft:shulker"
      },
      "base": "minecraft:item/shulker_box"
    },
    "transformation": {
      "left_rotation": [
        1.0,
        0.0,
        0.0,
        0.0
      ],
      "right_rotation": [
        -0.0,
        -0.0,
        -0.0,
        1.0
      ],
      "scale": [
        0.9995,
        0.9995,
        0.9995
      ],
      "translation": [
        0.5,
        1.4995,
        0.5
      ]
    }
  }
}